qa_project_gen/__init__.py
qa_project_gen/files_setup_helpers.py
qa_project_gen/main.py
qa_project_gen/project_setup_helpers.py
qa_project_gen/templates/.gitignore.j2
qa_project_gen/templates/README.md.j2
qa_project_gen/templates/playwright.config.ts.j2
qa_project_gen/templates/tsconfig.json.j2
qa_project_gen/templates/tests/back_end/feature_one/example_backend.spec.ts.j2
qa_project_gen/templates/tests/e2e/e2e_example.spec.ts.j2
qa_project_gen/templates/tests/front_end/feature_one/example_frontend.spec.ts.j2
qa_project_gen/templates/tests/support/POMs/feature_one/example.page.ts.j2
qa_project_gen/templates/tests/support/utils/fixtures.ts.j2
qa_project_gen/templates/tests/support/utils/helpers.ts.j2
qa_project_gen/templates/tests/support/utils/test-data.ts.j2
qa_project_gen-0.2.4.dist-info/METADATA
qa_project_gen-0.2.4.dist-info/WHEEL
qa_project_gen-0.2.4.dist-info/entry_points.txt
qa_project_gen-0.2.4.dist-info/top_level.txt
qa_project_gen-0.2.4.dist-info/RECORD
