Metadata-Version: 2.4
Name: qa-project-gen
Version: 0.2.4
Requires-Dist: jinja2
Dynamic: description
Dynamic: description-content-type
Dynamic: requires-dist
